{
  "Template": {
    "TemplateName": "CompanyEmail",
    "SubjectPart": "Data Deletion Request",
    "HtmlPart": "<p dir=\"ltr\">Dear {{companyName}},<\/p>\r\n            <br \/>\r\n            <p dir=\"ltr\">\r\n              I am submitting a request for implementation of the following\r\n              rights under Section 1798.105 of CCPA, Articles 7(3), 17 and 21 of\r\n              GDPR and other applicable privacy legislation which grant\r\n              individuals certain rights in relation to protection of their\r\n              personal data information:\r\n            <\/p>\r\n            <p dir=\"ltr\">\r\n              1) To obtain erasure (deletion) of personal data (information)\r\n              without undue delay;\r\n              <br \/>\r\n              2) To withdraw any consent given to the processing of personal\r\n              data (information);\r\n              <br \/>\r\n              3) To object to processing of personal data (information)\r\n              concerning the below individual, including but not limited to\r\n              profiling and direct marketing.\r\n            <\/p>\r\n            <br \/>\r\n            <p dir=\"ltr\">I can be identified by my details below:<\/p>\r\n            <br \/>\r\n            <p dir=\"ltr\">\r\n              <strong>Name: <\/strong>\r\n              {{name}}\r\n              <br \/>\r\n              <strong>Address: <\/strong>\r\n              {{street}}, {{city}}, {{country}}, {{postcode}}\r\n              <br \/>\r\n              <strong>E-mail address: <\/strong>\r\n              {{email}}\r\n            <br \/>\r\n              <strong>Phone: <\/strong>\r\n              {{phone}}\r\n            <\/p>\r\n            <br \/>\r\n            <p dir=\"ltr\">\r\n              Please confirm your compliance with the request without undue\r\n              delay and in any event within 45 (forty five) days of receipt of\r\n              this request.\r\n            <\/p>\r\n            <br \/>\r\n            <p dir=\"ltr\">Thank you.<\/p>\r\n            <p dir=\"ltr\">\r\n              {{name}}\r\n              <br \/>\r\n              <br \/>\r\n            <\/p>",
    "TextPart": "Dear {{companyName}},\r\n\r\nI am submitting a request for implementation of the following rights under Section 1798.105 of CCPA, Articles 7(3), 17 and 21 of GDPR and other applicable privacy legislation which grant individuals certain rights in relation to protection of their personal data information:\r\n\r\n1) To obtain erasure (deletion) of personal data (information) without undue delay;\r\n2) To withdraw any consent given to the processing of personal data (information);\r\n3) To object to processing of personal data (information) concerning the below individual, including but not limited to profiling and direct marketing.\r\n\r\nI can be identified by my details below:\r\n\r\nName: {{name}}\r\nAddress: {{street}}, {{city}}, {{country}}, {{postcode}}\r\nE-mail address: {{email}}\r\nPhone: {{phone}}\r\n\r\nPlease confirm your compliance with the request without undue delay and in any event within 45 (forty five) days of receipt of this request.\r\n\r\nThank you.\r\n\r\n{{name}}"
  }
}